sympyosis/__main__.py
sympyosis/app/__init__.py
sympyosis/app/app.py
sympyosis/app/args.py
sympyosis/config/__init__.py
sympyosis/config/config.py
sympyosis/config/service.py
sympyosis/exceptions.py
sympyosis/logger.py
sympyosis/options.py
sympyosis/services/__init__.py
sympyosis/services/interface_provider.py
sympyosis/services/service.py
sympyosis/services/service_manager.py
sympyosis-0.1.0.dist-info/LICENSE
sympyosis-0.1.0.dist-info/WHEEL
sympyosis-0.1.0.dist-info/METADATA
sympyosis-0.1.0.dist-info/RECORD
