Metadata-Version: 2.1
Name: sympyosis
Version: 0.1.0
Summary: Lightweight service orchistration & discovery.
License: MIT
Author: Zech Zimmerman
Author-email: hi@zech.codes
Requires-Python: >=3.10,<4.0
Classifier: License :: OSI Approved :: MIT License
Classifier: Programming Language :: Python :: 3
Classifier: Programming Language :: Python :: 3.10
Requires-Dist: bevy (>=1.0.1,<2.0.0)
Requires-Dist: fastapi (>=0.73.0,<0.74.0)
Requires-Dist: psutil (>=5.9.0,<6.0.0)
